qubit_measurement_analysis/__init__.py
qubit_measurement_analysis/_array_module.py
qubit_measurement_analysis/_sspd.py
qubit_measurement_analysis/_transformations.py
qubit_measurement_analysis/classification/__init__.py
qubit_measurement_analysis/classification/gaussian_mixture.py
qubit_measurement_analysis/classification/metrics.py
qubit_measurement_analysis/classification/temporal_post_processor.py
qubit_measurement_analysis/cli.py
qubit_measurement_analysis/cuda/_spd_kernels.cu
qubit_measurement_analysis/cuda/_sspd_self_pairwise_kernel.cu
qubit_measurement_analysis/cuda/_sspd_thrust.cu
qubit_measurement_analysis/cuda/spd.py
qubit_measurement_analysis/cuda/sspd.py
qubit_measurement_analysis/cython/_compilation_utils.py
qubit_measurement_analysis/cython/_sspd.pyx
qubit_measurement_analysis/cython/_transformations.pyx
qubit_measurement_analysis/cython/_transformations_wrapper.py
qubit_measurement_analysis/cython/classification/cttp_utils.pyx
qubit_measurement_analysis/cython/classification/temporal_post_processor.py
qubit_measurement_analysis/data/__init__.py
qubit_measurement_analysis/data/_distance_utils.py
qubit_measurement_analysis/data/shot_collection.py
qubit_measurement_analysis/data/single_shot.py
qubit_measurement_analysis/visualization/__init__.py
qubit_measurement_analysis/visualization/base_plotter.py
qubit_measurement_analysis/visualization/shot_collection_plotter.py
qubit_measurement_analysis/visualization/single_shot_plotter.py
qubit_measurement_analysis/visualization/utils.py
qubit_measurement_analysis-0.21.2.dist-info/LICENSE
qubit_measurement_analysis-0.21.2.dist-info/METADATA
qubit_measurement_analysis-0.21.2.dist-info/WHEEL
qubit_measurement_analysis-0.21.2.dist-info/RECORD
