Metadata-Version: 2.1
Name: qubit-measurement-analysis
Version: 0.21.2
Summary: Tools for analyzing in-phase / quadrature signals from superconducting quantum systems
Home-page: https://github.com/ikaryss/qubit-measurement-analysis
Author: Nikolai Zhitkov
Author-email: kolya.zhitkov@gmail.com
Requires-Python: >=3.9,<4.0
Classifier: Programming Language :: Python :: 3
Classifier: Programming Language :: Python :: 3.9
Classifier: Programming Language :: Python :: 3.10
Classifier: Programming Language :: Python :: 3.11
Classifier: Programming Language :: Python :: 3.12
Classifier: Programming Language :: Python :: 3.13
Requires-Dist: fastcluster (>=1.2.6,<2.0.0)
Requires-Dist: matplotlib (>=3.5.2)
Requires-Dist: numpy (<2.0.0)
Requires-Dist: scikit-learn (>=1.5.2,<2.0.0)
Requires-Dist: scipy (>=1.8.1)
Project-URL: Repository, https://github.com/ikaryss/qubit-measurement-analysis
